buspy/__init__.py
buspy/_event.py
buspy/_event_bus.py
buspy/_events_collector.py
buspy/exception.py
buspy-0.1.0.dist-info/METADATA
buspy-0.1.0.dist-info/WHEEL
buspy-0.1.0.dist-info/RECORD
