Metadata-Version: 2.1
Name: buspy
Version: 0.1.0
Summary: The BusPy Python Library provides a structured way to work with events within your application.
License: MIT
Author: Your Name
Author-email: you@example.com
Requires-Python: >=3.8.0
Classifier: License :: OSI Approved :: MIT License
Classifier: Programming Language :: Python :: 3
Classifier: Programming Language :: Python :: 3.8
Classifier: Programming Language :: Python :: 3.9
Classifier: Programming Language :: Python :: 3.10
Classifier: Programming Language :: Python :: 3.11
Requires-Dist: pyee (>=11.0.1) ; python_version >= "3.12"
Requires-Dist: pyee (>=9.0.0,<11.0.1) ; python_version < "3.12"
